vehicle_pedestrian/__init__.py
vehicle_pedestrian-0.0.1.dist-info/LICENSE
vehicle_pedestrian-0.0.1.dist-info/METADATA
vehicle_pedestrian-0.0.1.dist-info/WHEEL
vehicle_pedestrian-0.0.1.dist-info/top_level.txt
vehicle_pedestrian-0.0.1.dist-info/RECORD
