Metadata-Version: 2.1
Name: vehicle-pedestrian
Version: 0.0.1
Summary: Vehicle and pedestrian interaction
Home-page: https://github.com/ga74kud/vehicle_pedestrian
Author: Michael Hartmann
Author-email: michael.hartmann@v2c2.at
License: GNU GENERAL PUBLIC LICENSE
Platform: UNKNOWN
Classifier: Programming Language :: Python :: 3
Classifier: Operating System :: OS Independent
Requires-Python: >=3.6
Requires-Dist: scipy
Requires-Dist: numpy
Requires-Dist: reachab
Requires-Dist: matplotlib
Requires-Dist: argparse
Requires-Dist: shapely
